zope/app/testing/__init__.py
zope/app/testing/_compat.py
zope/app/testing/cookieTestOne.rst
zope/app/testing/cookieTestTwo.rst
zope/app/testing/dochttp.py
zope/app/testing/dochttp.rst
zope/app/testing/doctest.rst
zope/app/testing/empty.zcml
zope/app/testing/ftesting.zcml
zope/app/testing/functional.py
zope/app/testing/placelesssetup.py
zope/app/testing/setup.py
zope/app/testing/testing.py
zope/app/testing/tests.py
zope/app/testing/xmlrpc.py
zope/app/testing/xmlrpc.rst
zope/app/testing/ztapi.py
zope/app/testing/recorded/test0001.request
zope/app/testing/recorded/test0001.response
zope/app/testing/recorded/test0002.request
zope/app/testing/recorded/test0002.response
zope_app_testing-6.0.dist-info/licenses/LICENSE.txt
zope_app_testing-6.0.dist-info/METADATA
zope_app_testing-6.0.dist-info/WHEEL
zope_app_testing-6.0.dist-info/top_level.txt
zope_app_testing-6.0.dist-info/RECORD
