Metadata-Version: 2.4
Name: zope.app.testing
Version: 6.0
Summary: Zope Application Testing Support
Home-page: https://github.com/zopefoundation/zope.app.testing
Author: Zope Foundation and Contributors
Author-email: zope-dev@zope.dev
License: ZPL-2.1
Project-URL: Issue Tracker, https://github.com/zopefoundation/zope.app.testing/issues
Project-URL: Sources, https://github.com/zopefoundation/zope.app.testing
Keywords: zope3 test testing setup functional
Classifier: Development Status :: 5 - Production/Stable
Classifier: Environment :: Web Environment
Classifier: Intended Audience :: Developers
Classifier: License :: OSI Approved :: Zope Public License
Classifier: Programming Language :: Python
Classifier: Programming Language :: Python :: 3
Classifier: Programming Language :: Python :: 3.9
Classifier: Programming Language :: Python :: 3.10
Classifier: Programming Language :: Python :: 3.11
Classifier: Programming Language :: Python :: 3.12
Classifier: Programming Language :: Python :: 3.13
Classifier: Programming Language :: Python :: Implementation :: CPython
Classifier: Programming Language :: Python :: Implementation :: PyPy
Classifier: Natural Language :: English
Classifier: Operating System :: OS Independent
Classifier: Topic :: Internet :: WWW/HTTP
Classifier: Framework :: Zope :: 3
Requires-Python: >=3.9
License-File: LICENSE.txt
Requires-Dist: setuptools
Requires-Dist: zope.annotation
Requires-Dist: zope.app.appsetup>=3.11
Requires-Dist: zope.processlifetime
Requires-Dist: zope.app.debug
Requires-Dist: zope.app.dependable
Requires-Dist: zope.app.publication
Requires-Dist: zope.component>=3.8
Requires-Dist: zope.container
Requires-Dist: zope.i18n>=4.3.0
Requires-Dist: zope.interface
Requires-Dist: zope.password
Requires-Dist: zope.publisher
Requires-Dist: zope.schema
Requires-Dist: zope.security
Requires-Dist: zope.site
Requires-Dist: zope.testing
Requires-Dist: zope.traversing
Provides-Extra: test
Requires-Dist: ZODB; extra == "test"
Requires-Dist: zope.app.zcmlfiles; extra == "test"
Requires-Dist: zope.login; extra == "test"
Requires-Dist: zope.publisher>=3.12; extra == "test"
Requires-Dist: zope.securitypolicy; extra == "test"
Requires-Dist: zope.testrunner>=6.4; extra == "test"
Dynamic: author
Dynamic: author-email
Dynamic: classifier
Dynamic: description
Dynamic: home-page
Dynamic: keywords
Dynamic: license
Dynamic: license-file
Dynamic: project-url
Dynamic: provides-extra
Dynamic: requires-dist
Dynamic: requires-python
Dynamic: summary
